FPGA/Examples/full_adder/full_adder.v
module full_adder(a, b, cin, cout, sum);

input a, b, cin;
output cout, sum;

xor E_Or (net1, a, b);
and And  (net2, a, b);
xor E_Or1(sum, net1, cin);
and And2 (net4, net1, cin);
or  Or   (cout, net4, net2);

endmodule

FPGA/Examples/full_adder/full_adder_tb.v
`include "full_adder.v"

module full_adder_tb;

reg a, b, cin;
wire sum, cout;

initial
begin
	$dumpfile("./full_adder_tb.vcd");
	$dumpvars(0,full_adder_tb);
end

initial
begin: stimulus
	reg [3:0] invect;
	for(invect=0; invect < 8; invect = invect+1)
		begin
			{a, b, cin} = invect [3:0];
			#10 $display("abcin = %b, cout=%b, sum = %b", {a, b, cin}, cout, sum);
		end
end
	full_adder full_adder(.a(a),.b(b),.cin(cin),.cout(cout),.sum(sum));
endmodule

FPGA/Examples/full_adder/full_adder_tb.vcd
$date
	Mon May 22 17:21:57 2017
$end
$version
	Icarus Verilog
$end
$timescale
	1s
$end
$scope module full_adder_tb $end
$var wire 1 ! cout $end
$var wire 1 " sum $end
$var reg 1 # a $end
$var reg 1 $ b $end
$var reg 1 % cin $end
$scope module full_adder $end
$var wire 1 & a $end
$var wire 1 ' b $end
$var wire 1 ( cin $end
$var wire 1 ! cout $end
$var wire 1 ) net1 $end
$var wire 1 * net2 $end
$var wire 1 + net4 $end
$var wire 1 " sum $end
$upscope $end
$scope begin stimulus $end
$var reg 4 , invect [3:0] $end
$upscope $end
$upscope $end
$enddefinitions $end
#0
$dumpvars
b0 ,
0+
0*
0)
0(
0'
0&
0%
0$
0#
0"
0!
$end
#10
1"
1%
1(
b1 ,
#20
1)
1"
1$
1'
0%
0(
b10 ,
#30
1!
0"
1+
1%
1(
b11 ,
#40
0!
1"
0+
1#
1&
0$
0'
0%
0(
b100 ,
#50
1!
0"
1+
1%
1(
b101 ,
#60
0)
1*
0"
0+
1$
1'
0%
0(
b110 ,
#70
1"
1%
1(
b111 ,
#80
b1000 ,
