FPGA/Examples/bin2gray/bin2gray.v
module bin2gray(x1,x2,x3,x4,z1,z2,z3,z4);

input  x1,x2,x3,x4;
output z1,z2,z3,z4;

//wire z1,z2,z3,z4;

buf Buff (z1, x1);
xor E_Or (z2, x1, x2);
xor E_Or1(z3, x2, x3);
xor E_Or2(z4, x3, x4);

endmodule

FPGA/Examples/bin2gray/bin2gray_tb.v
`include "bin2gray.v"

module bin2gray_tb;

reg x1,x2,x3,x4;
wire z1,z2,z3,z4;

initial
begin
	$dumpfile("./bin2gray_tb.vcd");
	$dumpvars(0,bin2gray_tb);
end

initial
begin: stimulus
	reg [4:0] invect;
	for (invect = 0;invect < 16; invect = invect +1)
		begin
				{x1,x2,x3,x4} = invect [4:0];
				#10 $display("{x1x2x3x4}=%b, {z1z2z3z4}=%b",{x1,x2,x3,x4},{z1,z2,z3,z4});
		end
end

bin2gray BinToGray(.x1(x1),.x2(x2),.x3(x3),.x4(x4), 
						.z1(z1),.z2(z2),.z3(z3),.z4(z4));

endmodule

FPGA/Examples/bin2gray/bin2gray_tb.vcd
$date
	Mon May 22 16:43:09 2017
$end
$version
	Icarus Verilog
$end
$timescale
	1s
$end
$scope module bin2gray_tb $end
$var wire 1 ! z1 $end
$var wire 1 " z2 $end
$var wire 1 # z3 $end
$var wire 1 $ z4 $end
$var reg 1 % x1 $end
$var reg 1 & x2 $end
$var reg 1 ' x3 $end
$var reg 1 ( x4 $end
$scope module BinToGray $end
$var wire 1 ) x1 $end
$var wire 1 * x2 $end
$var wire 1 + x3 $end
$var wire 1 , x4 $end
$var wire 1 ! z1 $end
$var wire 1 " z2 $end
$var wire 1 # z3 $end
$var wire 1 $ z4 $end
$upscope $end
$scope begin stimulus $end
$var reg 5 - invect [4:0] $end
$upscope $end
$upscope $end
$enddefinitions $end
#0
$dumpvars
b0 -
0,
0+
0*
0)
0(
0'
0&
0%
0$
0#
0"
0!
$end
#10
1$
1(
1,
b1 -
#20
1#
1'
1+
0(
0,
b10 -
#30
0$
1(
1,
b11 -
#40
1"
1&
1*
0'
0+
0(
0,
b100 -
#50
1$
1(
1,
b101 -
#60
0#
1'
1+
0(
0,
b110 -
#70
0$
1(
1,
b111 -
#80
1!
1%
1)
0&
0*
0'
0+
0(
0,
b1000 -
#90
1$
1(
1,
b1001 -
#100
1#
1'
1+
0(
0,
b1010 -
#110
0$
1(
1,
b1011 -
#120
0"
1&
1*
0'
0+
0(
0,
b1100 -
#130
1$
1(
1,
b1101 -
#140
0#
1'
1+
0(
0,
b1110 -
#150
0$
1(
1,
b1111 -
#160
b10000 -
