FPGA/Examples/mev/mev.v
module mev(x1, x2, x3, x4, z1);

input x1,x2,x3,x4;
output z1;

and inst1 (net1, ~x1, ~x3, x4);
and inst2 (net2, ~x1, x2);
and inst3 (net3, x1, ~x2);
or  inst4 (z1, net1, net2, net3);

endmodule

FPGA/Examples/mev/mev_tb.v
`include "mev.v"

module mev_tb;

reg x1,x2,x3,x4;
wire z1;

initial
begin: apply_test
	reg [4:0] invect;
	$dumpfile("./mev_tb.vcd");
	$dumpvars(0,mev_tb);
	for (invect = 0; invect < 16; invect = invect+1)
		begin
			{x1, x2, x3, x4} = invect [4:0];
			#10 $display ("x1x2x3x4=%b, z1=%b", {x1,x2,x3,x4}, z1);
		end
end
mev inst1(.x1(x1),.x2(x2),.x3(x3), .x4(x4), .z1(z1));
endmodule

FPGA/Examples/mev/mev_tb.vcd
$date
	Mon May 22 12:57:21 2017
$end
$version
	Icarus Verilog
$end
$timescale
	1s
$end
$scope module mev_tb $end
$var wire 1 ! z1 $end
$var reg 1 " x1 $end
$var reg 1 # x2 $end
$var reg 1 $ x3 $end
$var reg 1 % x4 $end
$scope module inst1 $end
$var wire 1 & net1 $end
$var wire 1 ' net2 $end
$var wire 1 ( net3 $end
$var wire 1 ) x1 $end
$var wire 1 * x2 $end
$var wire 1 + x3 $end
$var wire 1 , x4 $end
$var wire 1 ! z1 $end
$upscope $end
$scope begin apply_test $end
$var reg 5 - invect [4:0] $end
$upscope $end
$upscope $end
$enddefinitions $end
#0
$dumpvars
b0 -
0,
0+
0*
0)
0(
0'
0&
0%
0$
0#
0"
0!
$end
#10
1!
1&
1%
1,
b1 -
#20
0!
0&
1$
1+
0%
0,
b10 -
#30
1%
1,
b11 -
#40
1!
1'
1#
1*
0$
0+
0%
0,
b100 -
#50
1&
1%
1,
b101 -
#60
0&
1$
1+
0%
0,
b110 -
#70
1%
1,
b111 -
#80
1(
0'
1"
1)
0#
0*
0$
0+
0%
0,
b1000 -
#90
1%
1,
b1001 -
#100
1$
1+
0%
0,
b1010 -
#110
1%
1,
b1011 -
#120
0!
0(
1#
1*
0$
0+
0%
0,
b1100 -
#130
1%
1,
b1101 -
#140
1$
1+
0%
0,
b1110 -
#150
1%
1,
b1111 -
#160
b10000 -
