FPGA/Examples/level_wait/level_wait.v
module level_wait;

reg mem_read, data_ready;
reg[7:0] data_bus, data;

always @(mem_read or data_bus or data_ready)
begin
	data = 0;
	while(mem_read == 1'b1) begin
		wait (data_ready == 1) #1 data=data_bus;
	end
end

initial begin
	$dumpfile("./level_wait.vcd");
	$dumpvars(0,level_wait);

	$monitor("%d Read = %b, Ready = %b, Data=%b", $time, mem_read, data_ready, data);

	data_bus = 0;
	mem_read = 0;
	data_ready = 0;
	#10 data_bus   = 8'hDE;
	#10 mem_read   = 1;
	#20 data_ready = 1;
	//#1  mem_read   = 1;
	#1  data_ready = 0;
	#10 data_bus   = 8'hAD;
	//#10  mem_read   = 1;
	#20  data_ready = 1;
	//#1   mem_read   = 1;
	#1   data_ready = 0;
	#10  $finish;
end
endmodule

FPGA/Examples/level_wait/level_wait.vcd
$date
	Wed May 17 16:42:54 2017
$end
$version
	Icarus Verilog
$end
$timescale
	1s
$end
$scope module level_wait $end
$var reg 8 ! data [7:0] $end
$var reg 8 " data_bus [7:0] $end
$var reg 1 # data_ready $end
$var reg 1 $ mem_read $end
$upscope $end
$enddefinitions $end
#0
$dumpvars
0$
0#
b0 "
b0 !
$end
#10
b11011110 "
#20
1$
#40
1#
#41
b11011110 !
0#
#51
b10101101 "
#71
1#
#72
b10101101 !
0#
