FPGA/Examples/mux_4to1/mux_4to1.v
module mux_4to1(d, s, en, z1);

input [3:0] d;
input [1:0] s;
input en;
output z1;

not inst1(net1, s[0]), inst2(net2, s[1]);

and inst3(net3, d[0], net1, net2, en),
		inst4(net4, d[1], s[0], net2, en),
		inst5(net5, d[2], net1, s[1], en),
		inst6(net6, d[3], s[0], s[1], en);

or  inst7(z1, net3, net4, net5, net6);

endmodule

FPGA/Examples/mux_4to1/mux_4to1_tb.v
`include "mux_4to1.v"

module mux_4to1_tb;

reg [3:0] d;
reg [1:0] s;
reg en;
wire z1;

initial
	$monitor($time,"ns, select:s=%b, inputs:d=%b, output:z1=%b",s,d,z1);

initial
	begin
	$dumpfile("./mux_4to1.vcd");
	$dumpvars(0,mux_4to1_tb);
	#0  s[0] = 1'b0; s[1] = 1'b0;
		  d[0] = 1'b0; d[1] = 1'b1; d[2] = 1'b0; d[3] = 1'b1;
		  en=1'b1;
	#10 s[0] = 1'b0; s[1] = 1'b0;
		  d[0] = 1'b1; d[1] = 1'b1; d[2] = 1'b0; d[3] = 1'b1;
		  en=1'b1;
	#10 s[0] = 1'b1; s[1] = 1'b0;
		  d[0] = 1'b1; d[1] = 1'b1; d[2] = 1'b0; d[3] = 1'b1;
		  en=1'b1;
	#10 s[0] = 1'b0; s[1] = 1'b1;
		  d[0] = 1'b1; d[1] = 1'b1; d[2] = 1'b0; d[3] = 1'b1;
		  en=1'b1;
	#10 s[0] = 1'b1; s[1] = 1'b0;
		  d[0] = 1'b1; d[1] = 1'b0; d[2] = 1'b0; d[3] = 1'b1;
		  en=1'b1;
	#10 s[0] = 1'b1; s[1] = 1'b1;
		  d[0] = 1'b1; d[1] = 1'b1; d[2] = 1'b0; d[3] = 1'b1;
		  en=1'b1;
	#10 s[0] = 1'b1; s[1] = 1'b1;
		  d[0] = 1'b1; d[1] = 1'b1; d[2] = 1'b0; d[3] = 1'b0;
		  en=1'b1;
	#10 s[0] = 1'b1; s[1] = 1'b1;
		  d[0] = 1'b1; d[1] = 1'b1; d[2] = 1'b0; d[3] = 1'b0;
		  en=1'b0;
	#10 $finish; 
	end

mux_4to1 inst1(.d(d), .s(s), .en(en), .z1(z1));

endmodule

FPGA/Examples/mux_4to1/mux_4to1.vcd
$date
	Mon May 22 15:31:30 2017
$end
$version
	Icarus Verilog
$end
$timescale
	1s
$end
$scope module mux_4to1_tb $end
$var wire 1 ! z1 $end
$var reg 4 " d [3:0] $end
$var reg 1 # en $end
$var reg 2 $ s [1:0] $end
$scope module inst1 $end
$var wire 4 % d [3:0] $end
$var wire 1 & en $end
$var wire 1 ' net1 $end
$var wire 1 ( net2 $end
$var wire 1 ) net3 $end
$var wire 1 * net4 $end
$var wire 1 + net5 $end
$var wire 1 , net6 $end
$var wire 2 - s [1:0] $end
$var wire 1 ! z1 $end
$upscope $end
$upscope $end
$enddefinitions $end
#0
$dumpvars
b0 -
0,
0+
0*
0)
1(
1'
1&
b1010 %
b0 $
1#
b1010 "
0!
$end
#10
1!
1)
b1011 "
b1011 %
b0 $
#20
0)
0'
1*
b1011 "
b1 $
b1 -
#30
0!
0(
1'
0*
b1011 "
b10 $
b10 -
#40
1(
0'
b1001 %
b1001 "
b1 $
b1 -
#50
1!
0(
1,
b1011 %
b1011 "
b11 -
b11 $
#60
0!
0,
b11 %
b11 "
b11 $
#70
0#
0&
b11 "
b11 $
